LICENSE
README.md
setup.py
kms_encryption_toolbox.egg-info/PKG-INFO
kms_encryption_toolbox.egg-info/SOURCES.txt
kms_encryption_toolbox.egg-info/dependency_links.txt
kms_encryption_toolbox.egg-info/entry_points.txt
kms_encryption_toolbox.egg-info/not-zip-safe
kms_encryption_toolbox.egg-info/requires.txt
kms_encryption_toolbox.egg-info/top_level.txt
kmsencryption/__init__.py
kmsencryption/__main__.py
kmsencryption/lib.py
kmsencryption/scripts/decrypt-and-start