Metadata-Version: 2.1
Name: kms-encryption-toolbox
Version: 0.2.4
Summary: Encryption toolbox to be used with the Amazon Key Management Service for securing your deployment secrets. It encapsulates the aws-encryption-sdk package to expose cmdline actions.
Home-page: https://github.com/ApplauseOSS/kms-encryption-toolbox
Author: Applause App Quality, Inc.
Author-email: ops@applause.com
License: MIT
Platform: UNKNOWN
License-File: LICENSE
